binaryplist/cli.py
binaryplist/plist.py
binaryplist/__init__.py
binaryplist-0.0.1.dist-info/DESCRIPTION.rst
binaryplist-0.0.1.dist-info/entry_points.txt
binaryplist-0.0.1.dist-info/METADATA
binaryplist-0.0.1.dist-info/metadata.json
binaryplist-0.0.1.dist-info/RECORD
binaryplist-0.0.1.dist-info/top_level.txt
binaryplist-0.0.1.dist-info/WHEEL
binplist/cli.py
binplist/plist.py
binplist/__init__.py
