Metadata-Version: 1.1
Name: binaryplist
Version: 0.0.1
Summary: Reads Apple binary plist files
Home-page: https://github.com/provegard/binaryplist
Author: Per Rovegard
Author-email: per@rovegard.se
License: BSD
Keywords: binary plist
Platform: any
Classifier: Programming Language :: Python
Classifier: Programming Language :: Python :: 2
Classifier: Programming Language :: Python :: 2.7
Classifier: Programming Language :: Python :: 3
Classifier: Programming Language :: Python :: 3.4
Classifier: Development Status :: 4 - Beta
Classifier: Natural Language :: English
Classifier: Environment :: Console
Classifier: Intended Audience :: Developers
Classifier: License :: OSI Approved :: BSD License
Classifier: Operating System :: OS Independent
Classifier: Topic :: Software Development :: Libraries :: Python Modules
